hittade/__init__.py
hittade/__main__.py
hittade-0.0.1.dist-info/entry_points.txt
hittade-0.0.1.dist-info/LICENSE
hittade-0.0.1.dist-info/WHEEL
hittade-0.0.1.dist-info/METADATA
hittade-0.0.1.dist-info/RECORD
