Metadata-Version: 2.1
Name: hittade
Version: 0.0.1
Summary: Command line tool to find and gather system information.
Author-email: Kushal Das <mail@kushaldas.in>
Requires-Python: >=3.6
Project-URL: Home, https://github.com/kushaldas/hittade
